getxpath/__init__.py
getxpath-1.0.1.dist-info/LICENSE.txt
getxpath-1.0.1.dist-info/METADATA
getxpath-1.0.1.dist-info/WHEEL
getxpath-1.0.1.dist-info/top_level.txt
getxpath-1.0.1.dist-info/RECORD
