Metadata-Version: 2.1
Name: getxpath
Version: 1.0.1
Summary: finding xpath of the element in the webpage
Home-page: UNKNOWN
Author: Mayank
Author-email: mayankkumar648@gmail.com
License: UNKNOWN
Platform: UNKNOWN
Classifier: Programming Language :: Python :: 3
Classifier: License :: OSI Approved :: MIT License
Classifier: Operating System :: OS Independent
Requires-Dist: requests
Requires-Dist: lxml
